{
  "generator-jhipster": {
    "applicationType": "gateway",
    "gitCompany": "",
    "baseName": "demoJhipster",
    "packageName": "xyz.adrianweb.demo",
    "packageFolder": "xyz/adrianweb/demo",
    "serverPort": 8080,
    "serviceDiscoveryType": false,
    "authenticationType": "jwt",
    "uaaBaseName": "../uaa",
    "cacheProvider": "no",
    "enableHibernateCache": false,
    "websocket": false,
    "databaseType": "mongodb",
    "devDatabaseType": "mongodb",
    "prodDatabaseType": "mongodb",
    "searchEngine": "elasticsearch",
    "enableSwaggerCodegen": false,
    "messageBroker": "kafka",
    "buildTool": "maven",
    "useSass": true,
    "clientPackageManager": "npm",
    "testFrameworks": ["cucumber"],
    "enableTranslation": true,
    "nativeLanguage": "en",
    "languages": ["en"],
    "clientFramework": "angularX",
    "jhiPrefix": "jhi",
    "jhipsterVersion": "6.8.0",
    "jwtSecretKey": "YTQ0ZDBkYzFjMDQ2OWQ4ODBiYzg2OTcxMzBhZjk3YTlhZmIzZTI4OWIxN2VhZTRhZGU4OWMxMTA4OWZlMzc2YmIxNTc2N2NiNTZkYzcyMGQyY2ZjOGQ3OTIxNTRjMTM4ODg3ZWQ2OTllMGI3MTNhMmI1Y2U3ODEzY2QyZjAwZWM=",
    "embeddableLaunchScript": false,
    "clientTheme": "none",
    "creationTimestamp": 1586530681623,
    "entitySuffix": "",
    "dtoSuffix": "DTO",
    "otherModules": [],
    "blueprints": []
  },
  "git-provider": "GitHub",
  "git-company": "AdrianBesleaga",
  "repository-name": "jhipster-sample-application"
}
